[
  {
    "featureType": "landscape.man_made",
    "elementType": "geometry.stroke",
    "stylers": [
      {
        "visibility": "on"
      }
    ]
  },
  {
    "featureType": "landscape.natural",
    "elementType": "geometry.fill",
    "stylers": [
      {
        "color": "#b8cb93"
      }
    ]
  },
  {
    "featureType": "poi",
    "stylers": [
      {
        "visibility": "on"
      }
    ]
  },
  {
    "featureType": "poi.attraction",
    "stylers": [
      {
        "visibility": "on"
      }
    ]
  },
  {
    "featureType": "poi.business",
    "stylers": [
      {
        "visibility": "on"
      }
    ]
  },
  {
    "featureType": "poi.medical",
    "stylers": [
      {
        "visibility": "on"
      }
    ]
  },
  {
    "featureType": "poi.park",
    "stylers": [
      {
        "visibility": "on"
      }
    ]
  },
  {
    "featureType": "poi.sports_complex",
    "stylers": [
      {
        "visibility": "on"
      }
    ]
  },
  {
    "featureType": "road",
    "elementType": "geometry.fill",
    "stylers": [
      {
        "saturation": -100
      },
      {
        "lightness": 100
      }
    ]
  },
  {
    "featureType": "road",
    "elementType": "geometry.stroke",
    "stylers": [
      {
        "saturation": -100
      },
      {
        "lightness": -5
      }
    ]
  },
  {
    "featureType": "water",
    "stylers": [
      {
        "hue": "#0088ff"
      },
      {
        "saturation": 43
      },
      {
        "lightness": -11
      }
    ]
  }
]